sy_python-0.2.4.dist-info/METADATA
sy_python-0.2.4.dist-info/WHEEL
sy_python-0.2.4.dist-info/entry_points.txt
sypy/__init__.py
sypy/__main__.py
sypy/_sypy.pyi
sypy/_sypy.pypy39-pp73-aarch64-linux-gnu.so
sypy/ls_types.py
sypy/ops_types.py
sypy/py.typed
sypy/remote.py
sy_python-0.2.4.dist-info/RECORD
