Metadata-Version: 2.4
Name: sy-python
Version: 0.2.4
Classifier: Development Status :: 4 - Beta
Classifier: Intended Audience :: Developers
Classifier: License :: OSI Approved :: MIT License
Classifier: Operating System :: MacOS
Classifier: Operating System :: POSIX :: Linux
Classifier: Operating System :: Microsoft :: Windows
Classifier: Programming Language :: Python :: 3
Classifier: Programming Language :: Python :: 3.8
Classifier: Programming Language :: Python :: 3.9
Classifier: Programming Language :: Python :: 3.10
Classifier: Programming Language :: Python :: 3.11
Classifier: Programming Language :: Python :: 3.12
Classifier: Programming Language :: Python :: Implementation :: CPython
Classifier: Programming Language :: Rust
Classifier: Topic :: System :: Archiving :: Backup
Classifier: Topic :: System :: Filesystems
Classifier: Typing :: Typed
Requires-Dist: pytest>=7.0 ; extra == 'dev'
Requires-Dist: tqdm>=4.0 ; extra == 'dev'
Provides-Extra: dev
Summary: Python bindings for sy - Modern file synchronization tool
Keywords: rsync,sync,file-transfer,backup
License: MIT
Requires-Python: >=3.8
Project-URL: Documentation, https://github.com/nijaru/sy#readme
Project-URL: Homepage, https://github.com/nijaru/sy
Project-URL: Repository, https://github.com/nijaru/sy
